health_azure/__init__.py
health_azure/amulet.py
health_azure/argparsing.py
health_azure/auth.py
health_azure/datasets.py
health_azure/himl.py
health_azure/himl_download.py
health_azure/himl_tensorboard.py
health_azure/logging.py
health_azure/mlflow_utils.py
health_azure/package_setup.py
health_azure/paths.py
health_azure/traverse.py
health_azure/utils.py
health_azure/examples/elevate_this.py
hi_ml_azure-0.5.4.dist-info/LICENSE
hi_ml_azure-0.5.4.dist-info/METADATA
hi_ml_azure-0.5.4.dist-info/WHEEL
hi_ml_azure-0.5.4.dist-info/entry_points.txt
hi_ml_azure-0.5.4.dist-info/top_level.txt
hi_ml_azure-0.5.4.dist-info/RECORD
