Metadata-Version: 2.1
Name: hi-ml-azure
Version: 0.5.4
Summary: Microsoft Health Futures package to elevate and monitor scripts to an AzureML workspace
Home-page: https://github.com/microsoft/hi-ml
Author: Biomedical Imaging Team @ Microsoft Health Futures
Author-email: innereyedev@microsoft.com
License: MIT License
Keywords: Health Futures,Health Intelligence,AzureML
Platform: UNKNOWN
Classifier: Development Status :: 3 - Alpha
Classifier: Intended Audience :: Science/Research
Classifier: Topic :: Scientific/Engineering :: Medical Science Apps.
Classifier: License :: OSI Approved :: MIT License
Classifier: Programming Language :: Python :: 3.9
License-File: LICENSE
Requires-Dist: azure-ai-ml (>=1.1.1)
Requires-Dist: azure-cli (>=2.30.0)
Requires-Dist: azureml-core (>=1.42.0)
Requires-Dist: azureml-dataset-runtime[fuse] (>=1.42.0)
Requires-Dist: azureml-mlflow (>=1.42.0)
Requires-Dist: azure-storage-blob (>=12.10.0)
Requires-Dist: azureml-tensorboard (>=1.42.0)
Requires-Dist: azureml-train-core (>=1.42.0)
Requires-Dist: conda-merge (>=0.1.5)
Requires-Dist: mlflow (>=1.29.0)
Requires-Dist: pandas (>=1.3.4)
Requires-Dist: param (<2.0,>=1.12)
Requires-Dist: protobuf (<4.0)
Requires-Dist: pysocks (>=1.5.8)
Requires-Dist: ruamel.yaml (>=0.16.12)
Requires-Dist: tensorboard (>=2.6.0)
Requires-Dist: typing-extensions (>=4.3.0)
